topsis/__init__.py
topsis/__main__.py
102017059_Aakanksha_Topsis-0.0.0.dist-info/LICENSE
102017059_Aakanksha_Topsis-0.0.0.dist-info/METADATA
102017059_Aakanksha_Topsis-0.0.0.dist-info/WHEEL
102017059_Aakanksha_Topsis-0.0.0.dist-info/entry_points.txt
102017059_Aakanksha_Topsis-0.0.0.dist-info/top_level.txt
102017059_Aakanksha_Topsis-0.0.0.dist-info/RECORD
