Metadata-Version: 2.1
Name: 102017059-Aakanksha-Topsis
Version: 0.0.0
Summary: Topsis Implementation
Home-page: https://github.com/aakanksha-17/102017059_Aakanksha_Topsis.git
Author: Aakanksha Pandey
Author-email: apandey1_be20@thapar.edu
License: MIT
Classifier: License :: OSI Approved :: MIT License
Classifier: Programming Language :: Python :: 3.6
Classifier: Programming Language :: Python :: 3.7
Classifier: Programming Language :: Python :: 3.8
License-File: LICENSE
